main.py
rsflow-0.1.0.dist-info/METADATA
rsflow-0.1.0.dist-info/WHEEL
rsflow-0.1.0.dist-info/top_level.txt
rsflow-0.1.0.dist-info/RECORD
