Metadata-Version: 2.4
Name: rsflow
Version: 0.1.0
Summary: Rustflow - Orchestration platform for tasks and assets fully backed by Rust (front and back)
Requires-Python: >=3.9
